Metadata-Version: 2.1
Name: topsis-daman
Version: 1.0.0
Summary: A Python package to implement Topsis analysis
Home-page: UNKNOWN
Author: Damanpreet Singh
Author-email: preetdamansingh1998@gmail.com
License: MIT
Platform: UNKNOWN
Classifier: License :: OSI Approved :: MIT License
Classifier: Programming Language :: Python :: 3
Classifier: Programming Language :: Python :: 3.7
